ansible_development_environment/__init__.py
ansible_development_environment/__main__.py
ansible_development_environment/_version.py
ansible_development_environment/arg_parser.py
ansible_development_environment/cli.py
ansible_development_environment/collection.py
ansible_development_environment/config.py
ansible_development_environment/output.py
ansible_development_environment/tree.py
ansible_development_environment/utils.py
ansible_development_environment/subcommands/__init__.py
ansible_development_environment/subcommands/checker.py
ansible_development_environment/subcommands/inspector.py
ansible_development_environment/subcommands/installer.py
ansible_development_environment/subcommands/lister.py
ansible_development_environment/subcommands/treemaker.py
ansible_development_environment/subcommands/uninstaller.py
ansible_development_environment-0.3.0.dist-info/LICENSE
ansible_development_environment-0.3.0.dist-info/METADATA
ansible_development_environment-0.3.0.dist-info/WHEEL
ansible_development_environment-0.3.0.dist-info/entry_points.txt
ansible_development_environment-0.3.0.dist-info/top_level.txt
ansible_development_environment-0.3.0.dist-info/RECORD
