Metadata-Version: 2.1
Name: ansible-development-environment
Version: 0.3.0
Summary: A pip-like ansible collection installer.
Author-email: "Bradley A. Thornton" <bthornto@redhat.com>
Maintainer-email: Bradley Thornton <bthornto@redhat.com>
License: GPL-3.0-only
Project-URL: changelog, https://github.com/cidrblock/ansible-development-environment/releases
Project-URL: documentation, https://ansible.readthedocs.io/projects/development-environment/
Project-URL: homepage, https://github.com/ansible/ansible-development-environment
Project-URL: repository, https://github.com/ansible/ansible-development-environment
Keywords: ansible
Classifier: Development Status :: 2 - Pre-Alpha
Classifier: Intended Audience :: Developers
Classifier: License :: OSI Approved :: GNU General Public License v3 (GPLv3)
Classifier: Operating System :: OS Independent
Classifier: Programming Language :: Python :: 3 :: Only
Classifier: Programming Language :: Python :: 3
Classifier: Programming Language :: Python :: 3.10
Classifier: Programming Language :: Python :: 3.11
Classifier: Programming Language :: Python :: 3.12
Classifier: Programming Language :: Python :: Implementation :: CPython
Classifier: Programming Language :: Python
Classifier: Topic :: Software Development
Classifier: Topic :: Utilities
Requires-Python: >=3.10
License-File: LICENSE
Requires-Dist: ansible-builder
Requires-Dist: pyyaml
Requires-Dist: subprocess-tee
Provides-Extra: dev
Requires-Dist: black ; extra == 'dev'
Requires-Dist: mypy ; extra == 'dev'
Requires-Dist: pip-tools ; extra == 'dev'
Requires-Dist: pre-commit ; extra == 'dev'
Requires-Dist: pydoclint ; extra == 'dev'
Requires-Dist: pytest ; extra == 'dev'
Requires-Dist: ruff ; extra == 'dev'
Requires-Dist: toml-sort ; extra == 'dev'
Requires-Dist: types-PyYAML ; extra == 'dev'
Provides-Extra: docs
Requires-Dist: mkdocs-ansible >=0.2.0 ; extra == 'docs'
Provides-Extra: test
Requires-Dist: pytest ; extra == 'test'
Requires-Dist: coverage[toml] ; extra == 'test'
Requires-Dist: pytest-xdist ; extra == 'test'
Requires-Dist: tox ; extra == 'test'
